vipcca/__init__.py
vipcca/model/__init__.py
vipcca/model/vipcca.py
vipcca/tools/__init__.py
vipcca/tools/parser.py
vipcca/tools/plotting.py
vipcca/tools/qqnorm.py
vipcca/tools/transferLabel.py
vipcca/tools/utils.py
vipcca-0.2.7.dist-info/METADATA
vipcca-0.2.7.dist-info/RECORD
vipcca-0.2.7.dist-info/WHEEL
vipcca-0.2.7.dist-info/top_level.txt
