Metadata-Version: 2.1
Name: vipcca
Version: 0.2.7
Summary: single cell integration
Home-page: https://github.com/jhu99/vipcca
Author: Jialu Hu
Author-email: jialuhu@umich.edu
License: MIT
Platform: UNKNOWN
Requires-Python: >=3.6
Requires-Dist: scanpy
Requires-Dist: tensorflow (==2.4.0)
Requires-Dist: anndata
Requires-Dist: scipy
Requires-Dist: pandas
Requires-Dist: seaborn
Requires-Dist: keras
Requires-Dist: python-igraph
Requires-Dist: louvain
Requires-Dist: h5py
Requires-Dist: future
